ConfluenceGenerator/__init__.py
ConfluenceGenerator/main.py
ConfluenceGenerator/utils.py
ConfluenceGenerator/process/__init__.py
ConfluenceGenerator/process/main.py
ConfluenceGenerator/process/plots.py
ConfluenceGenerator/process/tables.py
ConfluenceHelper/__init__.py
ConfluenceHelper/main.py
ConfluenceHelper/utils.py
ConfluenceHelper/process/__init__.py
ConfluenceHelper/process/main.py
ConfluenceHelper/process/plots.py
ConfluenceHelper/process/tables.py
confluence_generator-0.0.14.dist-info/METADATA
confluence_generator-0.0.14.dist-info/WHEEL
confluence_generator-0.0.14.dist-info/top_level.txt
confluence_generator-0.0.14.dist-info/RECORD
